YetAnotherOcrLibrary/__init__.py
YetAnotherOcrLibrary/version.py
YetAnotherOcrLibrary/exception/__init__.py
YetAnotherOcrLibrary/exception/ocr_error.py
YetAnotherOcrLibrary/keywords/__init__.py
YetAnotherOcrLibrary/keywords/detection.py
YetAnotherOcrLibrary/keywords/visualizer.py
YetAnotherOcrLibrary/model/__init__.py
YetAnotherOcrLibrary/model/object_detection.py
YetAnotherOcrLibrary/opencv/__init__.py
YetAnotherOcrLibrary/opencv/algorithm.py
YetAnotherOcrLibrary/opencv/template_matching.py
YetAnotherOcrLibrary/robotframework/__init__.py
YetAnotherOcrLibrary/robotframework/robotlog.py
YetAnotherOcrLibrary/util/__init__.py
YetAnotherOcrLibrary/util/data_type.py
YetAnotherOcrLibrary-0.0.6.dist-info/LICENSE
YetAnotherOcrLibrary-0.0.6.dist-info/METADATA
YetAnotherOcrLibrary-0.0.6.dist-info/WHEEL
YetAnotherOcrLibrary-0.0.6.dist-info/top_level.txt
YetAnotherOcrLibrary-0.0.6.dist-info/RECORD
