Metadata-Version: 2.1
Name: YetAnotherOcrLibrary
Version: 0.0.6
Summary: Object recognition library for Robot Framework
Home-page: https://github.com/Nepitwin/robotframework-yet-another-ocr-lib
Author: Andreas Sekulski
Author-email: andreas.sekulski@gmail.com
License: APACHE
Platform: Windows
Platform: Linux
Classifier: Programming Language :: Python :: 3
Classifier: Programming Language :: Python :: 3.8
Classifier: Programming Language :: Python :: 3.9
Classifier: Programming Language :: Python :: 3.10
Classifier: Programming Language :: Python :: 3.11
Classifier: Programming Language :: Python :: 3.12
Classifier: License :: OSI Approved :: Apache Software License
Classifier: Topic :: Software Development :: Testing
Classifier: Framework :: Robot Framework
Classifier: Framework :: Robot Framework :: Library
License-File: LICENSE
Requires-Dist: robotframework >=3.2.2
Requires-Dist: robotframework-pythonlibcore >=3.0.0
Requires-Dist: opencv-python >=4.10.0.82
Requires-Dist: numpy >=1.24.4
